{
    "title":"Տվյալներ բոլոր կոմպոնենտների համար",
    "headerPartners":"Գործընկերներ",
    "headerContact": "Կապ",
    "headerWhySmartEvent": "Ինչո՞ւ SmartEvent",
    "signIn": "Մուտք",
    "signUp": "ԳՐԱՆՑՎԵԼ",
    "mission" : "Մեր առաքելությունը",
    "missionText": "Մենք երիտասարդ թիմ ենք , և ստեղծել ենք 'Live chat' որը հաճախորդների հետ կապի մեջ լինելու ամենաարագ տարբերակն է,  խոսեք ձեր հաճախորդների հետ ժամանակի հենց իրական պահին ։",
    "adress" : "Հասցե : Հակոբ Հակոբյան 3",
    "phone" : "Հեռ : +374 99 09 09 09",
    "about" : "Մեր մասին",
    "home" : "Գլխավոր էջ",
    "aboutSmartEvent" : "SmartEvent-ի մասին",
    "ourPartners" : "Մեր գործընկերները",
    "ourTeam" : "Ահա մեր թիմը",
    "Gayane" : "Գայանե Հակոբյան",
    "Karo" : "Կարո Մուրադյան",
    "Karine": "Կարինե Ղազարյան",
    "Maria": "Մարիա Ստեփանյան",
    "socialSites" : "Սոցիալական Կայքեր",
    "why": "Ինչո՞ւ",
    "smart": "Smart",
    "event": "event",
    "support" : "Հաճախորդների սպասարկում",
    "liveChat" : "Առցանց զրույց",
    "MakeItPersonal" : "Դարձրու այն անձնական",
    "answersAndQuestion" :"Հարց ու պատասխան"
}